{
  "meta" : {
    "reportVersion" : "2.5"
  },
  "run" : {
    "version" : "2024.01.02-a6615a1-licensed",
    "creationTimestamp" : "2024-02-02T11:08:14.678Z",
    "command" : "dcover create --batch --report-file=report.json --coverage-reports --spring-integration-tests --verbose --working-directory=registry",
    "totalTime" : 59.597,
    "environmentDetectionTime" : 0.846,
    "indexingTime" : 0.372,
    "entryPointsTime" : 0.829,
    "generationTime" : 20.471,
    "timeToFirstTest" : 59.611,
    "timeToLastTest" : 53.437,
    "indexQueryTime" : 10.209,
    "verificationTime" : 0.0,
    "validationTime" : 0.0
  },
  "codes" : {
    "T005" : "Trivial constructor",
    "T006" : "Main method"
  },
  "summary" : {
    "classesCount" : 1,
    "methodsCount" : 2,
    "completeTestCount" : 0,
    "incompleteTestCount" : 0,
    "skeletonTestCount" : 0,
    "perMethodTestability" : {
      "T005" : 1,
      "T006" : 1
    },
    "perMethodOutcome" : {
      "T005" : 1,
      "T006" : 1
    }
  },
  "classes" : {
    "com.piggymetrics.registry.RegistryApplication" : {
      "methodsCount" : 2,
      "completeTestCount" : 0,
      "incompleteTestCount" : 0,
      "perMethodTestability" : {
        "T005" : 1,
        "T006" : 1
      },
      "perMethodOutcome" : {
        "T005" : 1,
        "T006" : 1
      }
    }
  },
  "methods" : {
    "com.piggymetrics.registry.RegistryApplication.<init>:()V" : {
      "completeTestCount" : 0,
      "incompleteTestCount" : 0,
      "perMethodTestability" : "T005",
      "perMethodOutcome" : "T005",
      "lineNumbers" : [
        9
      ]
    },
    "com.piggymetrics.registry.RegistryApplication.main:([Ljava/lang/String;)V" : {
      "completeTestCount" : 0,
      "incompleteTestCount" : 0,
      "perMethodTestability" : "T006",
      "perMethodOutcome" : "T006",
      "lineNumbers" : [
        12,
        13
      ]
    }
  }
}