{
  "meta" : {
    "reportVersion" : "2.5"
  },
  "run" : {
    "version" : "2024.04.02-e8d31c1-licensed",
    "creationTimestamp" : "2024-04-23T11:04:01.177Z",
    "command" : "dcover create --batch --report-file=report.json --coverage-reports --spring-integration-tests --verbose --working-directory=config",
    "totalTime" : 111.16,
    "environmentDetectionTime" : 0.691,
    "indexingTime" : 0.278,
    "entryPointsTime" : 0.672,
    "generationTime" : 42.928,
    "timeToFirstTest" : 92.393,
    "timeToLastTest" : 92.931,
    "indexQueryTime" : 9.531,
    "verificationTime" : 12.216,
    "validationTime" : 8.02
  },
  "codes" : {
    "R000" : "Success",
    "T000" : "Method eligible for test creation",
    "T005" : "Trivial constructor",
    "T006" : "Main method",
    "V000" : "Validated successfully"
  },
  "summary" : {
    "classesCount" : 2,
    "methodsCount" : 4,
    "completeTestCount" : 1,
    "incompleteTestCount" : 0,
    "skeletonTestCount" : 0,
    "perMethodTestability" : {
      "T000" : 2,
      "T005" : 1,
      "T006" : 1
    },
    "perMethodOutcome" : {
      "R000" : 1,
      "T005" : 2,
      "T006" : 1
    },
    "perTestOutcome" : {
      "R000" : 1
    },
    "perTestValidation" : {
      "V000" : 1
    }
  },
  "classes" : {
    "com.piggymetrics.config.ConfigApplication" : {
      "methodsCount" : 2,
      "completeTestCount" : 0,
      "incompleteTestCount" : 0,
      "perMethodTestability" : {
        "T005" : 1,
        "T006" : 1
      },
      "perMethodOutcome" : {
        "T005" : 1,
        "T006" : 1
      }
    },
    "com.piggymetrics.config.SecurityConfig" : {
      "methodsCount" : 2,
      "completeTestCount" : 1,
      "incompleteTestCount" : 0,
      "perMethodTestability" : {
        "T000" : 2
      },
      "perMethodOutcome" : {
        "R000" : 1,
        "T005" : 1
      },
      "perTestOutcome" : {
        "R000" : 1
      }
    }
  },
  "methods" : {
    "com.piggymetrics.config.ConfigApplication.<init>:()V" : {
      "completeTestCount" : 0,
      "incompleteTestCount" : 0,
      "perMethodTestability" : "T005",
      "perMethodOutcome" : "T005",
      "lineNumbers" : [
        9
      ]
    },
    "com.piggymetrics.config.ConfigApplication.main:([Ljava/lang/String;)V" : {
      "completeTestCount" : 0,
      "incompleteTestCount" : 0,
      "perMethodTestability" : "T006",
      "perMethodOutcome" : "T006",
      "lineNumbers" : [
        12,
        13
      ]
    },
    "com.piggymetrics.config.SecurityConfig.<init>:()V" : {
      "completeTestCount" : 0,
      "incompleteTestCount" : 0,
      "perMethodTestability" : "T000",
      "perMethodOutcome" : "T005",
      "lineNumbers" : [
        11
      ]
    },
    "com.piggymetrics.config.SecurityConfig.configure:(Lorg/springframework/security/config/annotation/web/builders/HttpSecurity;)V" : {
      "completeTestCount" : 1,
      "incompleteTestCount" : 0,
      "perMethodTestability" : "T000",
      "perMethodOutcome" : "R000",
      "perTestOutcome" : {
        "R000" : 1
      },
      "lineNumbers" : [
        15,
        16,
        17,
        18,
        19,
        20,
        21,
        23
      ]
    }
  }
}