{
  "meta" : {
    "reportVersion" : "2.5"
  },
  "run" : {
    "version" : "2023.07.01-327525f-licensed",
    "creationTimestamp" : "2023-07-04T16:56:52.623+01:00",
    "command" : "dcover create --batch --report-file=report.json --coverage-reports --spring-integration-tests --verbose --working-directory=turbine-stream-service",
    "totalTime" : 57.548,
    "environmentDetectionTime" : 0.509,
    "indexingTime" : 0.296,
    "entryPointsTime" : 0.484,
    "generationTime" : 21.414,
    "timeToFirstTest" : 57.553,
    "timeToLastTest" : 45.396,
    "indexQueryTime" : 9.914,
    "verificationTime" : 0.0,
    "validationTime" : 0.0
  },
  "codes" : {
    "T005" : "Trivial constructor",
    "T006" : "Main method"
  },
  "summary" : {
    "classesCount" : 1,
    "methodsCount" : 2,
    "completeTestCount" : 0,
    "incompleteTestCount" : 0,
    "skeletonTestCount" : 0,
    "perMethodTestability" : {
      "T005" : 1,
      "T006" : 1
    },
    "perMethodOutcome" : {
      "T005" : 1,
      "T006" : 1
    }
  },
  "classes" : {
    "com.piggymetrics.turbine.TurbineStreamServiceApplication" : {
      "methodsCount" : 2,
      "completeTestCount" : 0,
      "incompleteTestCount" : 0,
      "perMethodTestability" : {
        "T005" : 1,
        "T006" : 1
      },
      "perMethodOutcome" : {
        "T005" : 1,
        "T006" : 1
      }
    }
  },
  "methods" : {
    "com.piggymetrics.turbine.TurbineStreamServiceApplication.<init>:()V" : {
      "completeTestCount" : 0,
      "incompleteTestCount" : 0,
      "perMethodTestability" : "T005",
      "perMethodOutcome" : "T005",
      "lineNumbers" : [
        11
      ]
    },
    "com.piggymetrics.turbine.TurbineStreamServiceApplication.main:([Ljava/lang/String;)V" : {
      "completeTestCount" : 0,
      "incompleteTestCount" : 0,
      "perMethodTestability" : "T006",
      "perMethodOutcome" : "T006",
      "lineNumbers" : [
        14,
        15
      ]
    }
  }
}